phantom_cleaner/__init__.py
phantom_cleaner/cleaner.py
phantom_cleaner-0.1.0.dist-info/METADATA
phantom_cleaner-0.1.0.dist-info/WHEEL
phantom_cleaner-0.1.0.dist-info/top_level.txt
phantom_cleaner-0.1.0.dist-info/RECORD
