Metadata-Version: 2.4
Name: phantom_cleaner
Version: 0.1.0
Summary: A lightweight data cleaning library for Python
Home-page: https://github.com/yourusername/phantom_cleaner
Author: Arjun M
Classifier: Programming Language :: Python :: 3
Classifier: License :: OSI Approved :: MIT License
Classifier: Operating System :: OS Independent
Requires-Python: >=3.6
Requires-Dist: pandas>=1.0.0
Requires-Dist: numpy>=1.18.0
Requires-Dist: scikit-learn>=0.22.0
Dynamic: author
Dynamic: classifier
Dynamic: description
Dynamic: description-content-type
Dynamic: home-page
Dynamic: requires-dist
Dynamic: requires-python
Dynamic: summary
